Metadata-Version: 1.0
Name: pd-chunk
Version: 0.1
Summary: Pandas Row Manipulation
Home-page: UNKNOWN
Author: UNKNOWN
Author-email: UNKNOWN
License: UNKNOWN
Platform: UNKNOWN
